symwannier/__init__.py
symwannier/amn.py
symwannier/cli.py
symwannier/eig.py
symwannier/expand_wannier_inputs.py
symwannier/mmn.py
symwannier/nnkp.py
symwannier/sym.py
symwannier/timedata.py
symwannier/wannierize.py
symwannier/win.py
symwannier-1.1.0.dist-info/licenses/LICENSE
symwannier-1.1.0.dist-info/METADATA
symwannier-1.1.0.dist-info/WHEEL
symwannier-1.1.0.dist-info/entry_points.txt
symwannier-1.1.0.dist-info/top_level.txt
symwannier-1.1.0.dist-info/RECORD
