Metadata-Version: 2.4
Name: symWannier
Version: 1.1.0
Summary: A python package for computing symmetry adapted Wannier functions with irreducible BZ
Author-email: Takashi Koretsune <koretsune@cmpt.phys.tohoku.ac.jp>
License: GPLv2
License-File: LICENSE
Requires-Dist: requests
Requires-Dist: numpy
Requires-Dist: scipy
Requires-Dist: docopt
Provides-Extra: dev
Requires-Dist: pytest; extra == "dev"
Dynamic: license-file
